LICENSE
MANIFEST.in
README.rst
setup.py
django_quintet.egg-info/PKG-INFO
django_quintet.egg-info/SOURCES.txt
django_quintet.egg-info/dependency_links.txt
django_quintet.egg-info/top_level.txt
quintet/__init__.py
quintet/forms.py
quintet/models.py
quintet/utils.py